oarepo_model_builder_communities/__init__.py
oarepo_model_builder_communities/builders/__init__.py
oarepo_model_builder_communities/builders/communities_metadata.py
oarepo_model_builder_communities/builders/setup_cfg.py
oarepo_model_builder_communities/builders/templates/communities_metadata.py.jinja2
oarepo_model_builder_communities/builders/tests/__init__.py
oarepo_model_builder_communities/datatypes/components/__init__.py
oarepo_model_builder_communities/datatypes/components/communities_component.py
oarepo_model_builder_communities/datatypes/components/record_item.py
oarepo_model_builder_communities/datatypes/components/communities_model/__init__.py
oarepo_model_builder_communities/datatypes/components/communities_model/communities_metadata.py
oarepo_model_builder_communities/datatypes/components/communities_model/service.py
oarepo_model_builder_communities/tests_builders/__init__.py
oarepo_model_builder_communities/tests_builders/conftest.py
oarepo_model_builder_communities/tests_builders/parent_conftest.py
oarepo_model_builder_communities/tests_builders/record_communities/__init__.py
oarepo_model_builder_communities/tests_builders/record_communities/parent_conftest.py
oarepo_model_builder_communities/tests_builders/record_communities/test_resources.py
oarepo_model_builder_communities/tests_builders/record_communities/templates/parent_conftest.py.jinja2
oarepo_model_builder_communities/tests_builders/record_communities/templates/test_resources.py.jinja2
oarepo_model_builder_communities/tests_builders/templates/conftest.py.jinja2
oarepo_model_builder_communities-5.1.2.dist-info/METADATA
oarepo_model_builder_communities-5.1.2.dist-info/WHEEL
oarepo_model_builder_communities-5.1.2.dist-info/entry_points.txt
oarepo_model_builder_communities-5.1.2.dist-info/top_level.txt
oarepo_model_builder_communities-5.1.2.dist-info/RECORD
