Metadata-Version: 2.4
Name: oarepo-model-builder-communities
Version: 5.1.2
Requires-Dist: oarepo-model-builder-tests>=4.0.0
Requires-Dist: oarepo-model-builder-drafts>=4.0.0
Requires-Dist: oarepo-model-builder-requests>=4.0.0
Requires-Dist: oarepo-model-builder-workflows>=1.0.0
